{
  "Snailclimb/JavaGuide": {
    "owner": "Snailclimb",
    "name": "JavaGuide",
    "full_name": "Snailclimb/JavaGuide",
    "stars": 150609,
    "start_time": "2025-07-04T17:48:42.794595",
    "last_page": 59,
    "collected_count": 5,
    "total_processed": 5945,
    "status": "completed",
    "end_time": "2025-07-04T19:28:35.577590",
    "final_count": 5,
    "total_pages": 59
  },
  "krahets/hello-algo": {
    "owner": "krahets",
    "name": "hello-algo",
    "full_name": "krahets/hello-algo",
    "stars": 114046,
    "start_time": "2025-07-05T09:54:22.774758",
    "last_page": 22,
    "collected_count": 140,
    "total_processed": 2107,
    "status": "completed",
    "end_time": "2025-07-05T10:27:03.879504",
    "final_count": 140,
    "total_pages": 22
  },
  "GrowingGit/GitHub-Chinese-Top-Charts": {
    "owner": "GrowingGit",
    "name": "GitHub-Chinese-Top-Charts",
    "full_name": "GrowingGit/GitHub-Chinese-Top-Charts",
    "stars": 99901,
    "start_time": "2025-07-05T10:34:35.099940",
    "last_page": 11,
    "collected_count": 1,
    "total_processed": 1018,
    "status": "completed",
    "end_time": "2025-07-05T10:53:18.729232",
    "final_count": 1,
    "total_pages": 11
  },
  "iluwatar/java-design-patterns": {
    "owner": "iluwatar",
    "name": "java-design-patterns",
    "full_name": "iluwatar/java-design-patterns",
    "stars": 92197,
    "start_time": "2025-07-10T16:44:22.903661",
    "last_page": 44,
    "collected_count": 949,
    "total_processed": 4336,
    "status": "completed",
    "end_time": "2025-07-10T17:44:02.613803",
    "final_count": 949,
    "total_pages": 44
  }
}